LICENSE
README.md
setup.py
whocreatedme/__init__.py
whocreatedme/cli.py
whocreatedme/patch.py
whocreatedme.egg-info/PKG-INFO
whocreatedme.egg-info/SOURCES.txt
whocreatedme.egg-info/dependency_links.txt
whocreatedme.egg-info/entry_points.txt
whocreatedme.egg-info/requires.txt
whocreatedme.egg-info/top_level.txt