Metadata-Version: 2.1
Name: whocreatedme
Version: 1.0.0
Summary: Automate file origin tracking in your projects
Home-page: https://github.com/kristian-georgiev/whocreatedme
Author: Kristian Georgiev
Author-email: kris.georgiev@hey.com
Classifier: Programming Language :: Python :: 3
Classifier: License :: OSI Approved :: MIT License
Classifier: Operating System :: OS Independent
Requires-Python: >=3.6
License-File: LICENSE
